{
  "addBankCard.js": "addBankCard.js?v=ed619b1ab3",
  "borrow.js": "borrow.js?v=4ab861e630",
  "carChose.js": "carChose.js?v=057bee5eb4",
  "cityChose.js": "cityChose.js?v=417caffd57",
  "commissionPage.js": "commissionPage.js?v=e53d7ac55a",
  "comom.js": "comom.js?v=4318414399",
  "cusRecommend.js": "cusRecommend.js?v=6d97a528a8",
  "infoUpload.js": "infoUpload.js?v=e303d718cb",
  "jquery-2.1.0.js": "jquery-2.1.0.js?v=962a797ff6",
  "loanCalculate.js": "loanCalculate.js?v=513f7af4e4",
  "loanScheme.js": "loanScheme.js?v=e42a5c22da",
  "login.js": "login.js?v=5856d142db",
  "mui.indexedlist.js": "mui.indexedlist.js?v=93ab6d6249",
  "mui.min.js": "mui.min.js?v=b3cb6a77df",
  "myBorrow.js": "myBorrow.js?v=c182f8a505",
  "myBorrowDetail.js": "myBorrowDetail.js?v=2d34f46b83",
  "myRecommend.js": "myRecommend.js?v=384d341380",
  "myRecommendDetail.js": "myRecommendDetail.js?v=d528db0d78",
  "personalCenter.js": "personalCenter.js?v=52f4e9e682",
  "picker.js": "picker.js?v=068d829a95",
  "picker.min.js": "picker.min.js?v=4733a70345",
  "promptPage.js": "promptPage.js?v=687a002045",
  "withdrawal.js": "withdrawal.js?v=75b1be628f"
}